ciot_client2.py
cryptoiot_python_fork_sixtwo-0.0.1.dist-info/licenses/LICENSE
cryptoiot_python_fork_sixtwo-0.0.1.dist-info/METADATA
cryptoiot_python_fork_sixtwo-0.0.1.dist-info/WHEEL
cryptoiot_python_fork_sixtwo-0.0.1.dist-info/entry_points.txt
cryptoiot_python_fork_sixtwo-0.0.1.dist-info/top_level.txt
cryptoiot_python_fork_sixtwo-0.0.1.dist-info/RECORD
