Metadata-Version: 2.4
Name: CryptoIoT-Python-fork-sixtwo
Version: 0.0.1
Summary: CIoT Python Cient
Home-page: https://github.com/wladimir-computin/CryptoIoT-Python
Author: David Wischnjak
Requires-Python: >=3.6
License-File: LICENSE
Provides-Extra: full
Requires-Dist: pyserial; extra == "full"
Requires-Dist: pycryptodome; extra == "full"
Provides-Extra: crypto
Requires-Dist: pycryptodome; extra == "crypto"
Dynamic: author
Dynamic: home-page
Dynamic: license-file
Dynamic: provides-extra
Dynamic: requires-python
Dynamic: summary
